napari_spacemouse/__init__.py
napari_spacemouse/_napari.py
napari_spacemouse/_osx.py
napari_spacemouse/_spacemouse.py
napari_spacemouse/_widget.py
napari_spacemouse/napari.yaml
napari_spacemouse-0.1.0.dist-info/LICENSE
napari_spacemouse-0.1.0.dist-info/METADATA
napari_spacemouse-0.1.0.dist-info/WHEEL
napari_spacemouse-0.1.0.dist-info/entry_points.txt
napari_spacemouse-0.1.0.dist-info/top_level.txt
napari_spacemouse-0.1.0.dist-info/RECORD
