Metadata-Version: 2.1
Name: napari-spacemouse
Version: 0.1.0
Summary: 3DConnexion SpaceMouse support for napari
Home-page: https://github.com/tlambert03/napari-spacemouse
Author: Talley Lambert
Author-email: talley.lambert@gmail.com
License: BSD-3-Clause
Project-URL: Source Code, https://github.com/tlambert03/napari-spacemouse
Classifier: Development Status :: 2 - Pre-Alpha
Classifier: License :: OSI Approved :: BSD License
Classifier: Natural Language :: English
Classifier: Programming Language :: Python :: 3
Classifier: Programming Language :: Python :: 3 :: Only
Classifier: Programming Language :: Python :: 3.8
Classifier: Programming Language :: Python :: 3.9
Classifier: Programming Language :: Python :: 3.10
Requires-Python: >=3.8
License-File: LICENSE
Requires-Dist: hidapi
Provides-Extra: dev
Requires-Dist: black ; extra == 'dev'
Requires-Dist: flake8 ; extra == 'dev'
Requires-Dist: flake8-docstrings ; extra == 'dev'
Requires-Dist: ipython ; extra == 'dev'
Requires-Dist: isort ; extra == 'dev'
Requires-Dist: jedi (<0.18.0) ; extra == 'dev'
Requires-Dist: mypy ; extra == 'dev'
Requires-Dist: pre-commit ; extra == 'dev'
Requires-Dist: pydocstyle ; extra == 'dev'
Requires-Dist: pytest ; extra == 'dev'
Provides-Extra: testing
Requires-Dist: pytest ; extra == 'testing'
Requires-Dist: pytest-cov ; extra == 'testing'
Requires-Dist: tox ; extra == 'testing'
Requires-Dist: tox-conda ; extra == 'testing'
